process_tracing/__init__.py
process_tracing/constants.py
process_tracing/recording.py
process_tracing/tracing.py
process_tracing/sandbox/__init__.py
process_tracing/sandbox/server.py
process_tracing-0.1.0a11.dist-info/DESCRIPTION.rst
process_tracing-0.1.0a11.dist-info/METADATA
process_tracing-0.1.0a11.dist-info/metadata.json
process_tracing-0.1.0a11.dist-info/RECORD
process_tracing-0.1.0a11.dist-info/top_level.txt
process_tracing-0.1.0a11.dist-info/WHEEL
